jupyterlab_apod/__init__.py
jupyterlab_apod/_version.py
jupyterlab_apod/labextension/build_log.json
jupyterlab_apod/labextension/package.json
jupyterlab_apod/labextension/static/lib_index_js.83e1aba9264cea36e12d.js
jupyterlab_apod/labextension/static/lib_index_js.83e1aba9264cea36e12d.js.map
jupyterlab_apod/labextension/static/lib_index_js.864071ff0d156d2c95ec.js
jupyterlab_apod/labextension/static/lib_index_js.864071ff0d156d2c95ec.js.map
jupyterlab_apod/labextension/static/remoteEntry.8be62de024cd3dbaab8a.js
jupyterlab_apod/labextension/static/remoteEntry.8be62de024cd3dbaab8a.js.map
jupyterlab_apod/labextension/static/remoteEntry.cd5938aeb498975485e0.js.map
jupyterlab_apod/labextension/static/style.js
jupyterlab_apod/labextension/static/style_index_js.c20c85d18c06e52c0628.js
jupyterlab_apod/labextension/static/style_index_js.c20c85d18c06e52c0628.js.map
jupyterlab_apod/labextension/static/vendors-node_modules_css-loader_dist_runtime_api_js-node_modules_css-loader_dist_runtime_cssW-72eba1.ff9fd1918aad7223c83b.js
jupyterlab_apod/labextension/static/vendors-node_modules_css-loader_dist_runtime_api_js-node_modules_css-loader_dist_runtime_cssW-72eba1.ff9fd1918aad7223c83b.js.map
yamini_extn1-0.1.0.data/data/share/jupyter/labextensions/jupyterlab_apod/build_log.json
yamini_extn1-0.1.0.data/data/share/jupyter/labextensions/jupyterlab_apod/install.json
yamini_extn1-0.1.0.data/data/share/jupyter/labextensions/jupyterlab_apod/package.json
yamini_extn1-0.1.0.data/data/share/jupyter/labextensions/jupyterlab_apod/static/lib_index_js.83e1aba9264cea36e12d.js
yamini_extn1-0.1.0.data/data/share/jupyter/labextensions/jupyterlab_apod/static/lib_index_js.83e1aba9264cea36e12d.js.map
yamini_extn1-0.1.0.data/data/share/jupyter/labextensions/jupyterlab_apod/static/lib_index_js.864071ff0d156d2c95ec.js
yamini_extn1-0.1.0.data/data/share/jupyter/labextensions/jupyterlab_apod/static/lib_index_js.864071ff0d156d2c95ec.js.map
yamini_extn1-0.1.0.dist-info/LICENSE
yamini_extn1-0.1.0.dist-info/METADATA
yamini_extn1-0.1.0.dist-info/WHEEL
yamini_extn1-0.1.0.dist-info/top_level.txt
yamini_extn1-0.1.0.dist-info/RECORD
